docker_host_ip.py
docker_host_ip-0.0.3.dist-info/DESCRIPTION.rst
docker_host_ip-0.0.3.dist-info/METADATA
docker_host_ip-0.0.3.dist-info/RECORD
docker_host_ip-0.0.3.dist-info/WHEEL
docker_host_ip-0.0.3.dist-info/metadata.json
docker_host_ip-0.0.3.dist-info/top_level.txt
