Metadata-Version: 2.0
Name: docker-host-ip
Version: 0.0.3
Summary: A tool to get docker host ip or docker-container ip address.
Home-page: https://github.com/winkidney/docker-host-ip
Author: winkidney
Author-email: winkidney@gmail.com
License: MIT
Platform: UNKNOWN
